LICENSE
MANIFEST.in
README.md
setup.py
niceplot/__init__.py
niceplot/__main__.py
niceplot/draw1dratio.py
niceplot/draw2dhist.py
niceplot/draw2dscatter.py
niceplot/process_yaml.py
niceplot/reader.py
niceplot/utils.py
niceplot/data/ATLAS-CONF-2023-046_min_m_chi_BF_chi_10_to_gravitino_h_Exp.csv
niceplot/data/ATLAS-CONF-2023-046_min_m_chi_BF_chi_10_to_gravitino_h_Obs.csv
niceplot/data/Stitched_m_chi_10_m_chi_1p_Exp.csv
niceplot/data/Stitched_m_chi_10_m_chi_1p_Obs.csv
niceplot/data/Stitched_m_chi_10_min_m_mu_Exp.csv
niceplot/data/Stitched_m_chi_10_min_m_mu_Obs.csv
niceplotpy.egg-info/PKG-INFO
niceplotpy.egg-info/SOURCES.txt
niceplotpy.egg-info/dependency_links.txt
niceplotpy.egg-info/entry_points.txt
niceplotpy.egg-info/requires.txt
niceplotpy.egg-info/top_level.txt