Metadata-Version: 2.4
Name: niceplotpy
Version: 0.10.2
Summary: A package collecting things to make nice plots from root files
Home-page: https://gitlab.cern.ch/jwuerzin/nice-plot
Author: Jonas Wuerzinger
Author-email: jonas.wuerzinger@tum.de
Classifier: Development Status :: 3 - Alpha
Classifier: Intended Audience :: Science/Research
Classifier: License :: OSI Approved :: BSD License
Classifier: Operating System :: POSIX :: Linux
Classifier: Programming Language :: Python :: 3.11
Classifier: Programming Language :: Python :: 3.12
License-File: LICENSE
Requires-Dist: numpy
Requires-Dist: Click
Requires-Dist: matplotlib>=3.7.2
Requires-Dist: pyyaml
Requires-Dist: uproot>=5.0
Requires-Dist: awkward>=2.6.3
Requires-Dist: pandas
Requires-Dist: atlasify
Requires-Dist: importlib-metadata
Requires-Dist: tqdm
Requires-Dist: structlog
Dynamic: author
Dynamic: author-email
Dynamic: classifier
Dynamic: description
Dynamic: description-content-type
Dynamic: home-page
Dynamic: license-file
Dynamic: requires-dist
Dynamic: summary
